{
  "id": "HN-20200920-01",
  "type": "串词表达+价值引领+岗位适配类",
  "province": "湖南",
  "fullScore": 35,
  "question": "请从下列七组词语：\"青年、奋斗、幸福、担当、时代、理想、人生\"中任意选择三个词语串成一段话。",
  "dimensions": [
    {
      "name": "词语运用与逻辑",
      "score": 10
    },
    {
      "name": "价值导向与岗位追求",
      "score": 9
    },
    {
      "name": "省情与岗位适配",
      "score": 8
    },
    {
      "name": "语言表达与感染力",
      "score": 6
    },
    {
      "name": "创新思维",
      "score": 2
    }
  ],
  "coreKeywords": [
    "所选词语",
    "青年公职",
    "为民服务",
    "湖南发展"
  ],
  "strongKeywords": [
    "价值引领",
    "务实担当",
    "奋斗践行",
    "幸福内涵"
  ],
  "weakKeywords": [
    "三高四新",
    "湘易办",
    "基层治理",
    "民生保障"
  ],
  "bonusKeywords": [
    "案例融入",
    "场景化表达",
    "省情结合",
    "方言呼吁"
  ],
  "penaltyKeywords": [
    "词语堆砌",
    "逻辑混乱",
    "价值偏差",
    "脱离岗位",
    "内容空洞"
  ],
  "scoringCriteria": [
    "所选三个词语自然融入，无生硬堆砌，逻辑连贯，形成完整语义（10分）；",
    "内容正向积极，贴合国家公务员岗位追求，体现青年公职人员的担当与理想（9分）；",
    "融入湖南发展实际或公职人员履职场景，内容接地气、有温度（8分）；",
    "语言表达流畅优美、生动自然，有感染力，符合公职人员表达习惯（6分）；",
    "出现案例融入、场景化表达等特色方式，表述有个性、有亮点（2分）。"
  ],
  "deductionRules": [
    "词语使用牵强、无法形成完整语义，扣3-4分；",
    "内容消极，未体现公职人员担当与理想，扣3-4分；",
    "未结合湖南实际或岗位场景，泛泛而谈，扣3-4分；",
    "表达不流畅、口语化严重，扣2-3分；",
    "未使用指定词语或遗漏任意一个，扣8-10分。"
  ]
}