{
  "id": "HN-20200920-XZ-02",
  "type": "漫画解读+乡村振兴+实干导向类",
  "province": "湖南",
  "fullScore": 35,
  "question": "漫画题：村干部开着农耕机(农耕机上面写了\"扶贫号\")，笑着在耕田，农民在后面播种，旁边写了一个勤字，谈谈你的看法。",
  "dimensions": [
    {
      "name": "漫画解读与核心",
      "score": 9
    },
    {
      "name": "观点提炼与深度",
      "score": 8
    },
    {
      "name": "案例适配与本土化",
      "score": 7
    },
    {
      "name": "语言表达",
      "score": 7
    },
    {
      "name": "创新思维",
      "score": 4
    }
  ],
  "coreKeywords": [
    "扶贫",
    "干部带头",
    "群众参与",
    "勤劳实干",
    "湖南农村"
  ],
  "strongKeywords": [
    "乡村振兴",
    "领头雁",
    "内生动力",
    "产业发展",
    "勤字精神"
  ],
  "weakKeywords": [
    "脱贫致富",
    "十八洞村",
    "产业扶贫",
    "干群同心"
  ],
  "bonusKeywords": [
    "本土化案例",
    "实务延伸",
    "语言接地气",
    "性价比考量"
  ],
  "penaltyKeywords": [
    "解读偏差",
    "观点空洞",
    "案例泛化",
    "语言官方",
    "逻辑混乱"
  ],
  "scoringCriteria": [
    "准确把握'干部带头、群众参与、勤劳实干'核心，贴合乡镇实际（9分）；",
    "观点鲜明，结合湖南扶贫/乡村振兴实践，有深度、不空洞（8分）；",
    "融入湖南农村真实案例，体现'接地气、办实事'（7分）；",
    "语言朴实自然、条理清晰，符合乡镇干部表达习惯，有感染力（7分）；",
    "出现本土化案例、实务延伸等特色表述，贴合乡镇发展实际（4分）。"
  ],
  "deductionRules": [
    "未抓住'干部带头、勤'核心，或脱离乡镇/扶贫场景，扣7-9分；",
    "仅谈理论，未结合湖南农村实际，扣6-8分；",
    "未用湖南案例，或案例与漫画主题无关，扣5-7分；",
    "官话套话多，不接地气，扣3-4分；",
    "表述无序，未按'解读-观点-案例-总结'展开，扣3-4分。"
  ]
}